qcos_sdk/__init__.py
qcos_sdk/cli.pyi
qcos_sdk/client.pyi
qcos_sdk/models.pyi
qcos_sdk-2.2.0.dist-info/METADATA
qcos_sdk-2.2.0.dist-info/WHEEL
qcos_sdk-2.2.0.dist-info/entry_points.txt
qcos_sdk-2.2.0.dist-info/top_level.txt
qcos_sdk-2.2.0.dist-info/RECORD
