Metadata-Version: 2.4
Name: qcos-sdk
Version: 2.2.0
Summary: QCOS Quantum Circuit Optimization SDK
Author-email: SoftQuantus <contact@softquantus.com>
License: Proprietary
Classifier: Development Status :: 5 - Production/Stable
Classifier: Intended Audience :: Science/Research
Classifier: Topic :: Scientific/Engineering :: Physics
Classifier: Programming Language :: Python :: 3.10
Classifier: Programming Language :: Python :: 3.11
Classifier: Programming Language :: Python :: 3.12
Requires-Python: >=3.10
Requires-Dist: httpx>=0.27.0
Requires-Dist: pydantic>=2.0.0
Provides-Extra: qiskit
Requires-Dist: qiskit>=1.0.0; extra == "qiskit"
